wikipit.py
wikipit-1.0.4.dist-info/LICENSE
wikipit-1.0.4.dist-info/METADATA
wikipit-1.0.4.dist-info/WHEEL
wikipit-1.0.4.dist-info/entry_points.txt
wikipit-1.0.4.dist-info/top_level.txt
wikipit-1.0.4.dist-info/RECORD
