Metadata-Version: 2.1
Name: wikipit
Version: 1.0.4
Summary: A Command Line Tool to Search Wikipedia in the terminal.
Home-page: https://github.com/carrasquel/wikipit
Author: Nelson Carrasquel
Author-email: carrasquel@outlook.com
License: MIT
Platform: UNKNOWN
Requires-Dist: wikipedia
Requires-Dist: Click
